pypropel/__init__.py
pypropel/chem/Fingerprint.py
pypropel/chem/Physicochemical.py
pypropel/chem/SDF.py
pypropel/chem/Similarity.py
pypropel/chem/__init__.py
pypropel/convert.py
pypropel/dataset.py
pypropel/dist.py
pypropel/dna/__init__.py
pypropel/dna/sequence/Symbol.py
pypropel/dna/sequence/__init__.py
pypropel/eval.py
pypropel/external.py
pypropel/fpmsa.py
pypropel/fpseq.py
pypropel/fpsite.py
pypropel/fpstr.py
pypropel/io.py
pypropel/msa.py
pypropel/plot.py
pypropel/prot/__init__.py
pypropel/prot/feature/BasicUnit.py
pypropel/prot/feature/JSD.py
pypropel/prot/feature/PSSM.py
pypropel/prot/feature/Tinker.py
pypropel/prot/feature/__init__.py
pypropel/prot/feature/alignment/Composition.py
pypropel/prot/feature/alignment/Conservation.py
pypropel/prot/feature/alignment/Convert.py
pypropel/prot/feature/alignment/InformationTheory.py
pypropel/prot/feature/alignment/JSD.py
pypropel/prot/feature/alignment/MSA.py
pypropel/prot/feature/alignment/__init__.py
pypropel/prot/feature/alignment/external/jsd/._COPYING
pypropel/prot/feature/alignment/external/jsd/._README
pypropel/prot/feature/alignment/external/jsd/._distributions
pypropel/prot/feature/alignment/external/jsd/._matrix
pypropel/prot/feature/alignment/external/jsd/COPYING
pypropel/prot/feature/alignment/external/jsd/README
pypropel/prot/feature/alignment/external/jsd/alignment.scores
pypropel/prot/feature/alignment/external/jsd/distributions/._blosum62.distribution
pypropel/prot/feature/alignment/external/jsd/distributions/._pf.distribution
pypropel/prot/feature/alignment/external/jsd/distributions/._swissprot.distribution
pypropel/prot/feature/alignment/external/jsd/distributions/blosum62.distribution
pypropel/prot/feature/alignment/external/jsd/distributions/pf.distribution
pypropel/prot/feature/alignment/external/jsd/distributions/swissprot.distribution
pypropel/prot/feature/alignment/external/jsd/matrix/._blosum100.bla
pypropel/prot/feature/alignment/external/jsd/matrix/._blosum100.qij
pypropel-0.1.6.dist-info/LICENSE
pypropel-0.1.6.dist-info/METADATA
pypropel-0.1.6.dist-info/WHEEL
pypropel-0.1.6.dist-info/entry_points.txt
pypropel-0.1.6.dist-info/RECORD
